{
  "slug": "nishijin-hanakin-umeshu-2026",
  "title": "西新の華金は15時から！自分にご褒美をあげる「西のうめぼし」流",
  "date": "2026-05-15",
  "excerpt": "一週間お疲れ様でした！西新駅徒歩5分の「食堂 西のうめぼし」で、少し早めの時間からゆったりと自分を労う、最高に贅沢な華金の過ごし方をご提案します。",
  "image": "/images/テーブル上には何も乗せないように修正してください_202605151329.jpeg",
  "tags": [
    "華金, 西新, 昼飲み, 大衆食堂, 福岡グルメ"
  ],
  "body": "## 待ちに待った華金。西新の夜は少し早めにスタートしませんか？\n\n一週間の締めくくり、金曜日。お仕事帰りや家事の合間に「今日はちょっと飲みたいな」と思う瞬間はありませんか？福岡市早良区、活気あふれる西新の街で、そんな皆さまを温かくお迎えするのが「食堂 西のうめぼし」です。\n\n当店の自慢は、なんといっても「15時から呑める」こと。 「夜まで待てない！」「混み合う前にゆっくり始めたい」という方に、この早めのスタートが実はとっても好評なんです。西新駅から徒歩5分という好立地なので、お買い物帰りや、早めに切り上げた仕事帰りの一杯にも最適ですよ。\n\n## 常連さんに愛される「あの一品」\n\n「西のうめぼし」に来たら、まずはこれ。どこか懐かしい味わいの「肉豆腐」や、揚げたてサクサクの「アジフライ」をどうぞ。 大衆食堂ならではの温かみのある料理は、お一人さまでも気兼ねなく楽しめるよう、ちょうど良いボリュームでご用意しています。カウンター席でスタッフや隣のお客さまとゆるく会話を楽しむのも、西新という街の温かさを感じられる素敵な過ごし方です。\n\n## 週末へのスイッチを切り替える、自分だけの止まり木\n\n西新の街が本格的に賑わい始める夜を前に、一足お先に心地よく酔いしれる。 そんな少し贅沢で、自由な「自分時間」が翌日からの休日をさらに輝かせてくれます。\n\n店内は木のぬくもりを感じる落ち着いた雰囲気。初めての方でも、まるで行きつけのお店に来たような安心感を感じていただけるはずです。「お疲れ様」の一言とともに、心を込めたお料理とお酒をご用意してお待ちしております。\n\nご予約はお電話またはネット予約で。"
}